semantic_segmentation_augmentations/__init__.py
semantic_segmentation_augmentations/_modidx.py
semantic_segmentation_augmentations/artmix.py
semantic_segmentation_augmentations/carvemix.py
semantic_segmentation_augmentations/cutmixrandom.py
semantic_segmentation_augmentations/cutmixresizemix.py
semantic_segmentation_augmentations/cutmixricap.py
semantic_segmentation_augmentations/cutmixsemantic.py
semantic_segmentation_augmentations/cutouthideandseek.py
semantic_segmentation_augmentations/cutoutrandom.py
semantic_segmentation_augmentations/cutoutsemantic.py
semantic_segmentation_augmentations/hideandseek.py
semantic_segmentation_augmentations/holemakerattention.py
semantic_segmentation_augmentations/holemakerbounded.py
semantic_segmentation_augmentations/holemakerpoint.py
semantic_segmentation_augmentations/holemakerrandom.py
semantic_segmentation_augmentations/holemakerroi.py
semantic_segmentation_augmentations/holemakertechnique.py
semantic_segmentation_augmentations/holesfilling.py
semantic_segmentation_augmentations/iholemakertechnique.py
semantic_segmentation_augmentations/iholesfilling.py
semantic_segmentation_augmentations/regionmodifier.py
semantic_segmentation_augmentations/resizemix.py
semantic_segmentation_augmentations/ricap.py
semantic_segmentation_augmentations/selfmix.py
semantic_segmentation_augmentations/transparencemix.py
semantic_segmentation_augmentations-1.1.0.dist-info/LICENSE
semantic_segmentation_augmentations-1.1.0.dist-info/METADATA
semantic_segmentation_augmentations-1.1.0.dist-info/WHEEL
semantic_segmentation_augmentations-1.1.0.dist-info/entry_points.txt
semantic_segmentation_augmentations-1.1.0.dist-info/top_level.txt
semantic_segmentation_augmentations-1.1.0.dist-info/RECORD
