Metadata-Version: 2.1
Name: semantic-segmentation-augmentations
Version: 1.1.0
Summary: A library to apply some data augmentations in semantic segmentation problems
Home-page: https://github.com/ruescog/semantic_segmentation_augmentations
Author: ruescog
Author-email: ruescog@unirioja.es
License: Apache Software License 2.0
Keywords: nbdev jupyter notebook python
Classifier: Development Status :: 4 - Beta
Classifier: Intended Audience :: Developers
Classifier: Natural Language :: English
Classifier: Programming Language :: Python :: 3.7
Classifier: Programming Language :: Python :: 3.8
Classifier: Programming Language :: Python :: 3.9
Classifier: Programming Language :: Python :: 3.10
Classifier: License :: OSI Approved :: Apache Software License
Requires-Python: >=3.7
License-File: LICENSE
Requires-Dist: fastcore
Requires-Dist: pandas
Requires-Dist: numpy
Requires-Dist: fastai
Requires-Dist: opencv-python
Requires-Dist: albumentations
Provides-Extra: dev
